ods_tools/__init__.py
ods_tools/main.py
ods_tools/data/OpenExposureData_3.0.0Spec.json
ods_tools/data/OpenExposureData_3.0.1Spec.json
ods_tools/data/OpenExposureData_3.0.2Spec.json
ods_tools/data/OpenExposureData_3.0.3Spec.json
ods_tools/data/OpenExposureData_3.0.4Spec.json
ods_tools/data/OpenExposureData_3.1.0Spec.json
ods_tools/data/OpenExposureData_3.2.0Spec.json
ods_tools/data/OpenExposureData_3.3.0Spec.json
ods_tools/data/OpenExposureData_3.4.0Spec.json
ods_tools/data/OpenExposureData_3.4.1Spec.json
ods_tools/data/OpenExposureData_4.0.0Spec.json
ods_tools/data/__init__.py
ods_tools/data/analysis_settings_schema.json
ods_tools/data/model_settings_schema.json
ods_tools/odtf/__init__.py
ods_tools/odtf/controller.py
ods_tools/odtf/errors.py
ods_tools/odtf/mapper.py
ods_tools/odtf/notset.py
ods_tools/odtf/runner.py
ods_tools/odtf/validator.py
ods_tools/odtf/connector/__init__.py
ods_tools/odtf/connector/base.py
ods_tools/odtf/connector/csv.py
ods_tools/odtf/connector/db/__init__.py
ods_tools/odtf/connector/db/base.py
ods_tools/odtf/connector/db/errors.py
ods_tools/odtf/connector/db/mssql.py
ods_tools/odtf/connector/db/postgres.py
ods_tools/odtf/connector/db/sqlite.py
ods_tools/odtf/data/forms/metadata.yaml
ods_tools/odtf/transformers/__init__.py
ods_tools/odtf/transformers/errors.py
ods_tools/odtf/transformers/grammar.py
ods_tools/odtf/transformers/transform.py
ods_tools/odtf/transformers/transform_utils.py
ods_tools/oed/__init__.py
ods_tools/oed/common.py
ods_tools/oed/exposure.py
ods_tools/oed/forex.py
ods_tools/oed/oed_schema.py
ods_tools/oed/setting_schema.py
ods_tools/oed/settings.py
ods_tools/oed/source.py
ods_tools/oed/validator.py
ods_tools-4.0.4.dist-info/METADATA
ods_tools-4.0.4.dist-info/WHEEL
ods_tools-4.0.4.dist-info/entry_points.txt
ods_tools-4.0.4.dist-info/top_level.txt
ods_tools-4.0.4.dist-info/RECORD
