Metadata-Version: 2.4
Name: ods_tools
Version: 4.0.4
Summary: Tools to manage ODS files
Home-page: https://github.com/OasisLMF/OpenDataStandards
Author: Oasis LMF
Author-email: support@oasislmf.org
Requires-Python: >=3.8
Requires-Dist: pandas
Requires-Dist: numba
Requires-Dist: chardet
Requires-Dist: jsonschema>=4.0.1
Requires-Dist: jsonref
Requires-Dist: oasis-data-manager
Requires-Dist: packaging
Requires-Dist: tqdm
Provides-Extra: extra
Requires-Dist: PyYAML; extra == "extra"
Requires-Dist: lark; extra == "extra"
Requires-Dist: pyodbc; extra == "extra"
Requires-Dist: sqlparams; extra == "extra"
Requires-Dist: sqlparse; extra == "extra"
Requires-Dist: psycopg2; extra == "extra"
Dynamic: author
Dynamic: author-email
Dynamic: description
Dynamic: description-content-type
Dynamic: home-page
Dynamic: provides-extra
Dynamic: requires-dist
Dynamic: requires-python
Dynamic: summary
